[
    {
        "job_title": "Product Owner",
        "company_name": "MTI Technology Co., Ltd",
        "location": "Đà Nẵng, Hồ Chí Minh",
        "post_date": "Cập nhật: 08/05/2021 - Bạn còn 5 ngày để ứng tuyển"
    },
    {
        "job_title": "IT Manager (Shuttle Bus from HCMC)",
        "company_name": "Công Ty TNHH ON Semiconductor Việt Nam",
        "location": "Biên Hòa, Đồng Nai, Hồ Chí Minh",
        "post_date": "Cập nhật: 08/05/2021 - Bạn còn 11 ngày để ứng tuyển"
    },
    {
        "job_title": "Talent Acquisition Specialist",
        "company_name": "Tyme Digital",
        "location": "Hồ Chí Minh",
        "post_date": "Cập nhật: 08/05/2021 - Bạn còn 17 ngày để ứng tuyển"
    },
    {
        "job_title": "HR Consultant",
        "company_name": "Tyme Digital",
        "location": "Hồ Chí Minh",
        "post_date": "Cập nhật: 08/05/2021 - Bạn còn 17 ngày để ứng tuyển"
    },
    {
        "job_title": "IT Fresher Software - Mới Ra Trường/ < 1 Năm Kinh Nghiệm",
        "company_name": "Systemexe Vietnam",
        "location": "Hồ Chí Minh",
        "post_date": "Cập nhật: 08/05/2021 - Bạn còn 5 ngày để ứng tuyển"
    },
    {
        "job_title": "Tech Recruiter",
        "company_name": "Chi Nhánh Thành Phố Hồ Chí Minh - Công Ty Cổ Phần Doctor Anywhere Việt Nam",
        "location": "Hồ Chí Minh",
        "post_date": "Cập nhật: 08/05/2021 - Bạn còn 27 ngày để ứng tuyển"
    },
    {
        "job_title": "Project Manager (Open for Expat)",
        "company_name": "Capgemini Vietnam",
        "location": "Hồ Chí Minh",
        "post_date": "Cập nhật: 08/05/2021 - Bạn còn 4 ngày để ứng tuyển"
    },
    {
        "job_title": "Nhân Viên IT - Phần Mềm",
        "company_name": "Systemexe Vietnam",
        "location": "Hồ Chí Minh",
        "post_date": "Cập nhật: 08/05/2021 - Bạn còn 13 ngày để ứng tuyển"
    },
    {
        "job_title": "PHP Developer - Ít Nhất 1 Năm Kinh Nghiệm (Up to 1,300$)",
        "company_name": "Systemexe Vietnam",
        "location": "Hồ Chí Minh",
        "post_date": "Cập nhật: 08/05/2021 - Bạn còn 13 ngày để ứng tuyển"
    },
    {
        "job_title": "IT Officer",
        "company_name": "Vietnam Australia International School (Vas)",
        "location": "Hồ Chí Minh",
        "post_date": "Cập nhật: 08/05/2021 - Bạn còn 26 ngày để ứng tuyển"
    },
    {
        "job_title": "IT Infrastructure & Architecture Administrator (Network, Voice Ip, Firewall,..)",
        "company_name": "Công Ty Cổ Phần Giáo Dục Quốc Tế Việt Úc",
        "location": "Hồ Chí Minh",
        "post_date": "Cập nhật: 08/05/2021 - Bạn còn 18 ngày để ứng tuyển"
    },
    {
        "job_title": "Business Analyst (IT Industry)",
        "company_name": "Bbv Vietnam Co., Ltd",
        "location": "Hồ Chí Minh",
        "post_date": "Cập nhật: 08/05/2021 - Bạn còn 18 ngày để ứng tuyển"
    },
    {
        "job_title": "Senior Officer, Business Analyst",
        "company_name": "FWD Vietnam Life Insurance Company Limited",
        "location": "Hồ Chí Minh",
        "post_date": "Cập nhật: 08/05/2021 - Bạn còn 18 ngày để ứng tuyển"
    },
    {
        "job_title": "Software Consultant",
        "company_name": "Công Ty CP Giải Pháp Kinh Doanh Nền Tảng - Basebs",
        "location": "Hồ Chí Minh",
        "post_date": "Cập nhật: 08/05/2021 - Bạn còn 18 ngày để ứng tuyển"
    },
    {
        "job_title": "Lập Trình Viên",
        "company_name": "Công Ty TNHH Thiết Bị Minh Tâm (Mitalab Co., Ltd)",
        "location": "Hà Nội, Hồ Chí Minh",
        "post_date": "Cập nhật: 08/05/2021 - Bạn còn 18 ngày để ứng tuyển"
    },
    {
        "job_title": "Chief Operation Officer (For Software Company)",
        "company_name": "Aperia Vietnam Co Ltd.,",
        "location": "Hồ Chí Minh",
        "post_date": "Cập nhật: 08/05/2021 - Bạn còn 18 ngày để ứng tuyển"
    },
    {
        "job_title": "Technical Lead (Director Level)",
        "company_name": "Primus’ Client – A Japanese IT Corporation",
        "location": "Hồ Chí Minh",
        "post_date": "Cập nhật: 08/05/2021 - Bạn còn 14 ngày để ứng tuyển"
    },
    {
        "job_title": "IT Project Management Specialist (Infra/network/hardware)",
        "company_name": "LOTTE Data Communication Company Limited Vietnam",
        "location": "Hồ Chí Minh",
        "post_date": "Cập nhật: 07/05/2021 - Bạn còn 7 ngày để ứng tuyển"
    },
    {
        "job_title": "IT Application Support - 6 Months contract",
        "company_name": "FORD Vietnam Limited",
        "location": "Hà Nội, Hồ Chí Minh",
        "post_date": "Cập nhật: 07/05/2021 - Bạn còn 7 ngày để ứng tuyển"
    },
    {
        "job_title": "Nhân Viên IT Phần Mềm",
        "company_name": "Công Ty Tnhh, Liên Doanh Vĩnh Hưng (TMI Viet Nam)",
        "location": "Hồ Chí Minh",
        "post_date": "Cập nhật: 07/05/2021 - Bạn còn 25 ngày để ứng tuyển"
    },
    {
        "job_title": "[HOT] ERP Support",
        "company_name": "Công Ty TNHH Sản Xuất Thương Mại Đầu Tư Nhôm An Lập Phát",
        "location": "Hồ Chí Minh",
        "post_date": "Cập nhật: 07/05/2021 - Bạn còn 7 ngày để ứng tuyển"
    },
    {
        "job_title": "Engineering Manager (Director Level)",
        "company_name": "Primus’ Client – A Japanese IT Corporation",
        "location": "Hồ Chí Minh",
        "post_date": "Cập nhật: 07/05/2021 - Bạn còn 14 ngày để ứng tuyển"
    },
    {
        "job_title": "IT Solution Architect (Chinese Mandarin Speaking)",
        "company_name": "DXC Vietnam",
        "location": "Hồ Chí Minh",
        "post_date": "Cập nhật: 07/05/2021 - Bạn còn 13 ngày để ứng tuyển"
    },
    {
        "job_title": "IT Business Analysis Senior Officer/ Supervisor",
        "company_name": "Mirae Asset Prevoir Life Insurance Company Ltd.",
        "location": "Hồ Chí Minh",
        "post_date": "Cập nhật: 07/05/2021 - Bạn còn 13 ngày để ứng tuyển"
    },
    {
        "job_title": "02 Nhân Viên IT",
        "company_name": "Công Ty TNHH SMC (Manufacturing) Việt Nam",
        "location": "Biên Hòa, Đồng Nai, Hồ Chí Minh",
        "post_date": "Cập nhật: 07/05/2021 - Bạn còn 20 ngày để ứng tuyển"
    },
    {
        "job_title": "Security Officer - Security Department – IT Division – H.o",
        "company_name": "Ngân Hàng TNHH Indovina",
        "location": "Hồ Chí Minh",
        "post_date": "Cập nhật: 07/05/2021 - Bạn còn 20 ngày để ứng tuyển"
    },
    {
        "job_title": "Nhân Viên Tư Vấn Giải Pháp Phần Mềm / IT Solution Consulting (Pre-Sales)",
        "company_name": "Fujifilm Business Innovation Vietnam Co., Ltd.",
        "location": "Hà Nội, Hồ Chí Minh",
        "post_date": "Cập nhật: 07/05/2021 - Bạn còn 13 ngày để ứng tuyển"
    },
    {
        "job_title": "Senior Business Analyst",
        "company_name": "Prudential Vietnam Assurance",
        "location": "Hồ Chí Minh",
        "post_date": "Cập nhật: 07/05/2021 - Bạn còn 17 ngày để ứng tuyển"
    },
    {
        "job_title": "Data Engineer",
        "company_name": "AIA Vietnam (Great Place To Work® Certified)",
        "location": "Hồ Chí Minh",
        "post_date": "Cập nhật: 07/05/2021 - Bạn còn 20 ngày để ứng tuyển"
    },
    {
        "job_title": "Senior Technical Support Specialist",
        "company_name": "Hitachi Vantara Vietnam Co., Ltd.",
        "location": "Hồ Chí Minh",
        "post_date": "Cập nhật: 07/05/2021 - Bạn còn 28 ngày để ứng tuyển"
    },
    {
        "job_title": "IT Recruiter",
        "company_name": "Công Ty TNHH Money Forward Việt Nam",
        "location": "Hồ Chí Minh",
        "post_date": "Cập nhật: 07/05/2021 - Bạn còn 28 ngày để ứng tuyển"
    },
    {
        "job_title": "Software Engineering",
        "company_name": "FPT Software",
        "location": "Hồ Chí Minh",
        "post_date": "Cập nhật: 06/05/2021 - Bạn còn 27 ngày để ứng tuyển"
    },
    {
        "job_title": "Recruitment Executive",
        "company_name": "Niteco (Vietnam) CO., Ltd",
        "location": "Hà Nội, Hồ Chí Minh",
        "post_date": "Cập nhật: 06/05/2021 - Bạn còn 13 ngày để ứng tuyển"
    },
    {
        "job_title": "Technical Service Specialist",
        "company_name": "ELCA Information Technology (Vietnam) Limited",
        "location": "Hồ Chí Minh",
        "post_date": "Cập nhật: 06/05/2021 - Bạn còn 6 ngày để ứng tuyển"
    },
    {
        "job_title": "Quality Control",
        "company_name": "SCC ( Specialist Computer Centres) Ltd.",
        "location": "Hồ Chí Minh",
        "post_date": "Cập nhật: 06/05/2021 - Bạn còn 6 ngày để ứng tuyển"
    },
    {
        "job_title": "Microsoft Teams Support Engineer (MS 365)",
        "company_name": "Robert Bosch Engineering Vietnam",
        "location": "Hồ Chí Minh",
        "post_date": "Cập nhật: 06/05/2021 - Bạn còn 27 ngày để ứng tuyển"
    },
    {
        "job_title": "IT Business Analysis Assistant Manager(MỚI)",
        "company_name": "Dai-Ichi Life Vietnam",
        "location": "Hồ Chí Minh",
        "post_date": "Cập nhật: 06/05/2021 - Bạn còn 19 ngày để ứng tuyển"
    },
    {
        "job_title": "IT Project Manager - Corporate Strategic Projects(MỚI)",
        "company_name": "FE CREDIT",
        "location": "Hồ Chí Minh",
        "post_date": "Cập nhật: 06/05/2021 - Bạn còn 19 ngày để ứng tuyển"
    },
    {
        "job_title": "Sr. IT Application Manager",
        "company_name": "Công Ty Cổ Phần Y Khoa Hoàn Mỹ",
        "location": "Hồ Chí Minh",
        "post_date": "Cập nhật: 06/05/2021 - Bạn còn 16 ngày để ứng tuyển"
    },
    {
        "job_title": "Chuyên Viên Phát Triển Ứng Dụng (.NET)(MỚI)",
        "company_name": "Công Ty Cổ Phần Chuỗi Thực Phẩm TH",
        "location": "Hồ Chí Minh",
        "post_date": "Cập nhật: 06/05/2021 - Bạn còn 19 ngày để ứng tuyển"
    },
    {
        "job_title": ".Net Team Lead – Up to $2500(MỚI)",
        "company_name": "FPT Software",
        "location": "Hồ Chí Minh",
        "post_date": "Cập nhật: 06/05/2021 - Bạn còn 19 ngày để ứng tuyển"
    },
    {
        "job_title": "[URGENT] Sales Manager in Software Industry",
        "company_name": "Innotech Viet Nam Corp",
        "location": "Hồ Chí Minh",
        "post_date": "Cập nhật: 06/05/2021 - Bạn còn 6 ngày để ứng tuyển"
    },
    {
        "job_title": "Bridge Software Engineer/ Japanese Speaking Software Engineer",
        "company_name": "Hitachi Vantara Vietnam Co., Ltd.",
        "location": "Hồ Chí Minh",
        "post_date": "Cập nhật: 06/05/2021 - Bạn còn 6 ngày để ứng tuyển"
    },
    {
        "job_title": "IT Governance and Compliance Manager - Information Security",
        "company_name": "Ngân Hàng TMCP Á Châu (ACB)",
        "location": "Hồ Chí Minh",
        "post_date": "Cập nhật: 06/05/2021 - Bạn còn 27 ngày để ứng tuyển"
    },
    {
        "job_title": "IT Service and Partner Management Manager",
        "company_name": "Prudential Vietnam Assurance",
        "location": "Hồ Chí Minh",
        "post_date": "Cập nhật: 05/05/2021 - Bạn còn 26 ngày để ứng tuyển"
    },
    {
        "job_title": "IT Business Application Support Officer",
        "company_name": "La Vie Limited Liability Company",
        "location": "Hồ Chí Minh",
        "post_date": "Cập nhật: 05/05/2021 - Bạn còn 26 ngày để ứng tuyển"
    },
    {
        "job_title": "Project Manager / BrSE (Japanese, 2000$-4000$)",
        "company_name": "Raksul Viet Nam Co.ltd",
        "location": "Hồ Chí Minh",
        "post_date": "Cập nhật: 05/05/2021 - Bạn còn 26 ngày để ứng tuyển"
    },
    {
        "job_title": "HR Assistant - Recruiter (13 Mil - 15 Mil++)",
        "company_name": "Nakivo",
        "location": "Hồ Chí Minh",
        "post_date": "Cập nhật: 05/05/2021 - Bạn còn 12 ngày để ứng tuyển"
    },
    {
        "job_title": "Senior IT Recruiter",
        "company_name": "PYCOGROUP",
        "location": "Hồ Chí Minh",
        "post_date": "Cập nhật: 05/05/2021 - Bạn còn 11 ngày để ứng tuyển"
    },
    {
        "job_title": "R&d Developer - Manager",
        "company_name": "Công Ty TMA",
        "location": "Hồ Chí Minh",
        "post_date": "Cập nhật: 05/05/2021 - Bạn còn 11 ngày để ứng tuyển"
    },
    {
        "job_title": "Chuyên Viên Hỗ Trợ Ứng Dụng (Application Support Senior Officer/officer)",
        "company_name": "Công Ty Cổ Phần Chứng Khoán SSI",
        "location": "Hồ Chí Minh",
        "post_date": "Cập nhật: 06/05/2021 - Bạn còn 27 ngày để ứng tuyển"
    },
    {
        "job_title": "Product Owner (Ưu Tiên Nữ, 5 Năm Kinh Nghiệm Trở Lên)",
        "company_name": "Công Ty Cổ Phần Wee Digital",
        "location": "Hồ Chí Minh",
        "post_date": "Cập nhật: 30/04/2021 - Bạn còn 6 ngày để ứng tuyển"
    },
    {
        "job_title": "Senior Consultant | Technology Consulting Services (Banking & Finance Sector) | HCMC & Hanoi Office",
        "company_name": "Ernst & Young Vietnam Limited",
        "location": "Hà Nội, Hồ Chí Minh",
        "post_date": "Cập nhật: 07/05/2021 - Bạn còn 28 ngày để ứng tuyển"
    },
    {
        "job_title": "Chuyên Viên Lập Trình Và Vận Hành Hệ Thống",
        "company_name": "Công Ty TNHH Chứng Khoán ACB",
        "location": "Hồ Chí Minh",
        "post_date": "Cập nhật: 05/05/2021 - Bạn còn 26 ngày để ứng tuyển"
    },
    {
        "job_title": "Senior Shopify Developer",
        "company_name": "Williams Commerce",
        "location": "Hồ Chí Minh",
        "post_date": "Cập nhật: 01/05/2021 - Bạn còn 7 ngày để ứng tuyển"
    },
    {
        "job_title": "Online Development Manager(MỚI)",
        "company_name": "Mirae Asset Finance Company (Viet Nam) Ltd.",
        "location": "Hồ Chí Minh",
        "post_date": "Cập nhật: Hôm nay - Bạn còn 19 ngày để ứng tuyển"
    },
    {
        "job_title": "Intermediate Analyst, Infrastructure and Operations (DevOps)",
        "company_name": "Sun Life Vietnam (Sun Life)",
        "location": "Hồ Chí Minh",
        "post_date": "Cập nhật: 04/05/2021 - Bạn còn 25 ngày để ứng tuyển"
    },
    {
        "job_title": "[URGENT] Senior ReactJS Developer (4-6 Years)",
        "company_name": "Tập Đoàn CNTT Toàn Cầu HCL Technologies",
        "location": "Hà Nội, Hồ Chí Minh",
        "post_date": "Cập nhật: 08/05/2021 - Bạn còn 18 ngày để ứng tuyển"
    },
    {
        "job_title": "[HCMC] - Senior Product Owner - [4000$~7000$](MỚI)",
        "company_name": "IT Production Company",
        "location": "Hồ Chí Minh",
        "post_date": "Cập nhật: Hôm nay - Bạn còn 19 ngày để ứng tuyển"
    },
    {
        "job_title": "[HCMC] - DevOps Leader - [2000$~2500$](MỚI)",
        "company_name": "IT Production Company",
        "location": "Hồ Chí Minh",
        "post_date": "Cập nhật: Hôm nay - Bạn còn 19 ngày để ứng tuyển"
    },
    {
        "job_title": "[HCMC] - Mobile Tech Lead- [2000$~3000$](MỚI)",
        "company_name": "IT Production Company",
        "location": "Hồ Chí Minh",
        "post_date": "Cập nhật: Hôm nay - Bạn còn 19 ngày để ứng tuyển"
    },
    {
        "job_title": "[HCMC] - Solution Architect (Cloud, AWS , DevOps) - [4000$~6000$](MỚI)",
        "company_name": "IT Production Company",
        "location": "Hồ Chí Minh",
        "post_date": "Cập nhật: Hôm nay - Bạn còn 19 ngày để ứng tuyển"
    },
    {
        "job_title": "[HCMC] - NodeJS Developer - [1000$~1500$](MỚI)",
        "company_name": "IT Product Company",
        "location": "Hồ Chí Minh",
        "post_date": "Cập nhật: Hôm nay - Bạn còn 19 ngày để ứng tuyển"
    },
    {
        "job_title": "[HCMC] - Senior Fullstack (Java / JS / PHP / Ror / Python/ Go) Developer - [2000$~3000$](MỚI)",
        "company_name": "IT Company",
        "location": "Hồ Chí Minh",
        "post_date": "Cập nhật: Hôm nay - Bạn còn 19 ngày để ứng tuyển"
    },
    {
        "job_title": "[HCMC] - Software Developer / BrSE (Japanese N3) [2000$~3000$](MỚI)",
        "company_name": "IT Company",
        "location": "Hồ Chí Minh",
        "post_date": "Cập nhật: Hôm nay - Bạn còn 19 ngày để ứng tuyển"
    },
    {
        "job_title": "[HCMC] - Senior Business Analyst [40Mil ~60Mil Gross]",
        "company_name": "IT Production Company",
        "location": "Hồ Chí Minh",
        "post_date": "Cập nhật: 08/05/2021 - Bạn còn 18 ngày để ứng tuyển"
    },
    {
        "job_title": "[HCMC] - Solution Architect (Cloud, AWS , DevOps) - [4000$~6000$]",
        "company_name": "IT Production Company",
        "location": "Hồ Chí Minh",
        "post_date": "Cập nhật: 08/05/2021 - Bạn còn 14 ngày để ứng tuyển"
    },
    {
        "job_title": "[HCMC] - Senior Software Developer - [2000$~3000$]",
        "company_name": "IT Company",
        "location": "Hồ Chí Minh",
        "post_date": "Cập nhật: 08/05/2021 - Bạn còn 14 ngày để ứng tuyển"
    },
    {
        "job_title": "[HCMC] - Senior Fullstack (Java / JS / PHP / Ror / Python/ Go) Developer - [2000$~3000$]",
        "company_name": "IT Company",
        "location": "Hồ Chí Minh",
        "post_date": "Cập nhật: 08/05/2021 - Bạn còn 14 ngày để ứng tuyển"
    },
    {
        "job_title": "[HCMC] - Senior Fullstack Developer - [2000$~3000$]",
        "company_name": "IT Company",
        "location": "Hồ Chí Minh",
        "post_date": "Cập nhật: 08/05/2021 - Bạn còn 14 ngày để ứng tuyển"
    },
    {
        "job_title": "[HCMC] - Backend Engineer (Java) - [2000$~3500$]",
        "company_name": "IT Production Company",
        "location": "Hồ Chí Minh",
        "post_date": "Cập nhật: 07/05/2021 - Bạn còn 13 ngày để ứng tuyển"
    },
    {
        "job_title": "[HCMC] - Backend Engineer (Java) - [2000$~3500$]",
        "company_name": "IT Production Company",
        "location": "Hồ Chí Minh",
        "post_date": "Cập nhật: 07/05/2021 - Bạn còn 13 ngày để ứng tuyển"
    },
    {
        "job_title": "[HCMC] - Senior Fullstack Developer - [2000$~3000$]",
        "company_name": "IT Company",
        "location": "Hồ Chí Minh",
        "post_date": "Cập nhật: 07/05/2021 - Bạn còn 13 ngày để ứng tuyển"
    },
    {
        "job_title": "[HCMC] - Software Developer / BrSE (Japanese N3) [2000$~3000$]",
        "company_name": "IT Company",
        "location": "Hồ Chí Minh",
        "post_date": "Cập nhật: 07/05/2021 - Bạn còn 13 ngày để ứng tuyển"
    },
    {
        "job_title": "[HCMC] - NodeJS Developer - [1000$~1500$]",
        "company_name": "IT Product Company",
        "location": "Hồ Chí Minh",
        "post_date": "Cập nhật: 05/05/2021 - Bạn còn 26 ngày để ứng tuyển"
    },
    {
        "job_title": "[HCMC] - Solution Architect (Cloud, AWS , DevOps) - [4000$~6000$]",
        "company_name": "IT Production Company",
        "location": "Hồ Chí Minh",
        "post_date": "Cập nhật: 05/05/2021 - Bạn còn 26 ngày để ứng tuyển"
    },
    {
        "job_title": "[HCMC] - Mobile Tech Lead- [2000$~3000$]",
        "company_name": "IT Production Company",
        "location": "Hồ Chí Minh",
        "post_date": "Cập nhật: 05/05/2021 - Bạn còn 26 ngày để ứng tuyển"
    },
    {
        "job_title": "[HCMC] - Senior Product Owner - [4000$~7000$]",
        "company_name": "IT Production Company",
        "location": "Hồ Chí Minh",
        "post_date": "Cập nhật: 05/05/2021 - Bạn còn 26 ngày để ứng tuyển"
    },
    {
        "job_title": "[HCMC] - Senior Fullstack (Java / JS / PHP / Ror / Python/ Go) Developer - [2000$~3000$]",
        "company_name": "IT Company",
        "location": "Hồ Chí Minh",
        "post_date": "Cập nhật: 05/05/2021 - Bạn còn 26 ngày để ứng tuyển"
    },
    {
        "job_title": "[HCMC] - NodeJS Developer - [1000$~1500$]",
        "company_name": "IT Product Company",
        "location": "Hồ Chí Minh",
        "post_date": "Cập nhật: 29/04/2021 - Bạn còn 5 ngày để ứng tuyển"
    },
    {
        "job_title": "[HCMC] - Senior ABAP Developer (Japanese N2) - Up to 3000$",
        "company_name": "IT Company",
        "location": "Hồ Chí Minh",
        "post_date": "Cập nhật: 29/04/2021 - Bạn còn 5 ngày để ứng tuyển"
    },
    {
        "job_title": "[HCMC | New Company] - Backend Engineer (Java / AWS) - [1500~2000$]",
        "company_name": "Global IT Product Company",
        "location": "Hồ Chí Minh",
        "post_date": "Cập nhật: 07/05/2021 - Bạn còn 13 ngày để ứng tuyển"
    },
    {
        "job_title": "[HCMC] - Project Manager (Japanese N2) - [3000$~5000$]",
        "company_name": "Japanese IT Company",
        "location": "Hồ Chí Minh",
        "post_date": "Cập nhật: 07/05/2021 - Bạn còn 13 ngày để ứng tuyển"
    },
    {
        "job_title": "[HCMC] - Project Manager (Japanese N2) - [3000$~5000$]",
        "company_name": "Japanese IT Company",
        "location": "Hồ Chí Minh",
        "post_date": "Cập nhật: 05/05/2021 - Bạn còn 26 ngày để ứng tuyển"
    },
    {
        "job_title": "[ New Company] - Backend Engineer (Java / AWS) - [1500~2000$]",
        "company_name": "Global IT Product Company",
        "location": "Hồ Chí Minh",
        "post_date": "Cập nhật: 05/05/2021 - Bạn còn 26 ngày để ứng tuyển"
    },
    {
        "job_title": "[HCMC | New Company] - Cloud Data Engineer AWS - [2000$~2500$]",
        "company_name": "Global IT Product Company",
        "location": "Hồ Chí Minh",
        "post_date": "Cập nhật: 05/05/2021 - Bạn còn 26 ngày để ứng tuyển"
    },
    {
        "job_title": "[HCMC] - Web Developer (Python) [3000$~4000$]",
        "company_name": "US Based IT Company",
        "location": "Hồ Chí Minh",
        "post_date": "Cập nhật: 08/05/2021 - Bạn còn 14 ngày để ứng tuyển"
    },
    {
        "job_title": "[HCMC] - Data Development Engineer (Python) [ 3000$~5000$]",
        "company_name": "US Based IT Company",
        "location": "Hồ Chí Minh",
        "post_date": "Cập nhật: 08/05/2021 - Bạn còn 14 ngày để ứng tuyển"
    },
    {
        "job_title": "[HCMC] - Web Developer (Python) [3000$~4000$]",
        "company_name": "US Based IT Company",
        "location": "Hồ Chí Minh",
        "post_date": "Cập nhật: 05/05/2021 - Bạn còn 26 ngày để ứng tuyển"
    },
    {
        "job_title": "[HCMC] - Web Developer (Python) [3000$~4000$]",
        "company_name": "US Based IT Company",
        "location": "Hồ Chí Minh",
        "post_date": "Cập nhật: 29/04/2021 - Bạn còn 5 ngày để ứng tuyển"
    },
    {
        "job_title": "Chuyên Viên Phân Tích Nghiệp Vụ BA ( Salary up to 1500$)",
        "company_name": "Công Ty Cổ Phần Giải Pháp ERP - ITG",
        "location": "Hà Nội, Hồ Chí Minh",
        "post_date": "Cập nhật: 26/04/2021 - Bạn còn 6 ngày để ứng tuyển"
    },
    {
        "job_title": "IT Application Support",
        "company_name": "Jabil Vietnam Company Limited",
        "location": "Hồ Chí Minh",
        "post_date": "Cập nhật: 24/04/2021 - Hết hạn HÔM NAY!"
    },
    {
        "job_title": "IT - Backend Developer (.Net, Java, NodeJS)",
        "company_name": "Ngân Hàng TMCP Á Châu (ACB)",
        "location": "Hồ Chí Minh",
        "post_date": "Cập nhật: 22/04/2021 - Bạn còn 2 ngày để ứng tuyển"
    },
    {
        "job_title": "IT Manager",
        "company_name": "Công Ty TNHH Speak Up Viet Nam",
        "location": "Hồ Chí Minh",
        "post_date": "Cập nhật: 20/04/2021 - Hết hạn HÔM NAY!"
    },
    {
        "job_title": "Global IT Services Manager",
        "company_name": "Swiss Post Solutions Ltd.",
        "location": "Hồ Chí Minh",
        "post_date": "Cập nhật: 07/05/2021 - Bạn còn 13 ngày để ứng tuyển"
    },
    {
        "job_title": "Senior IT Mobile App Business Analyst",
        "company_name": "FE CREDIT",
        "location": "Hồ Chí Minh",
        "post_date": "Cập nhật: 04/05/2021 - Bạn còn 4 ngày để ứng tuyển"
    },
    {
        "job_title": "Product Owner/ IT Supervisor",
        "company_name": "DHL Supply Chain",
        "location": "Hồ Chí Minh",
        "post_date": "Cập nhật: 07/05/2021 - Bạn còn 20 ngày để ứng tuyển"
    },
    {
        "job_title": "General Manager - IT (M/f)",
        "company_name": "Cooptalis",
        "location": "Hồ Chí Minh",
        "post_date": "Cập nhật: 07/05/2021 - Bạn còn 17 ngày để ứng tuyển"
    },
    {
        "job_title": "Nhân Viên IT",
        "company_name": "Công Ty Cổ Phần Đầu Tư Hồng Hạc",
        "location": "Hồ Chí Minh",
        "post_date": "Cập nhật: 04/05/2021 - Bạn còn 14 ngày để ứng tuyển"
    },
    {
        "job_title": "[HCMC] - New IT Company - HR Manager",
        "company_name": "IT Company",
        "location": "Hồ Chí Minh",
        "post_date": "Cập nhật: 03/05/2021 - Bạn còn 13 ngày để ứng tuyển"
    },
    {
        "job_title": "Nhân Viên IT",
        "company_name": "Trường Cao Đẳng Quốc Tế Kent",
        "location": "Hồ Chí Minh",
        "post_date": "Cập nhật: 25/04/2021 - Bạn còn 5 ngày để ứng tuyển"
    },
    {
        "job_title": "Chuyên Viên IT Helpdesk",
        "company_name": "Công Ty Cổ Phần Nhựa Opec",
        "location": "Hồ Chí Minh",
        "post_date": "Cập nhật: 21/04/2021 - Bạn còn 1 ngày để ứng tuyển"
    },
    {
        "job_title": "Senior Technical Recruiter (IT Company)",
        "company_name": "Aperia Solutions (Vietnam) Co Ltd.,",
        "location": "Hồ Chí Minh",
        "post_date": "Cập nhật: 07/05/2021 - Bạn còn 28 ngày để ứng tuyển"
    },
    {
        "job_title": "Talent Acquisition Executive (IT - HN/HCM)",
        "company_name": "Innotech Viet Nam Corp",
        "location": "Hà Nội, Hồ Chí Minh",
        "post_date": "Cập nhật: 07/05/2021 - Bạn còn 28 ngày để ứng tuyển"
    },
    {
        "job_title": "Talent Acquisition Specialist - IT",
        "company_name": "Cooptalis",
        "location": "Hồ Chí Minh",
        "post_date": "Cập nhật: 07/05/2021 - Bạn còn 28 ngày để ứng tuyển"
    },
    {
        "job_title": "Kỹ Thuật Viên IT và Quản Trị Web",
        "company_name": "Công Ty Cổ Phần Giata",
        "location": "Hồ Chí Minh",
        "post_date": "Cập nhật: 30/04/2021 - Bạn còn 6 ngày để ứng tuyển"
    },
    {
        "job_title": "[URGENT] Sales Support - IT Services, B2B Sales",
        "company_name": "LOTTE Data Communication Company Limited Vietnam",
        "location": "Hồ Chí Minh",
        "post_date": "Cập nhật: 20/04/2021 - Hết hạn HÔM NAY!"
    },
    {
        "job_title": "Employee Engagement Manager (For IT Division)",
        "company_name": "Home Credit Vietnam - Https://career.homecredit.vn/",
        "location": "Hồ Chí Minh",
        "post_date": "Cập nhật: 02/05/2021 - Bạn còn 8 ngày để ứng tuyển"
    },
    {
        "job_title": "Nhân Viên Tuyển Dụng (IT Recruiter)",
        "company_name": "FPT Information System (Fis)",
        "location": "Hà Nội, Hồ Chí Minh",
        "post_date": "Cập nhật: 30/04/2021 - Bạn còn 10 ngày để ứng tuyển"
    },
    {
        "job_title": "HR GA Manager - New IT Company in Vietnam",
        "company_name": "Navigos Search's Client",
        "location": "Hồ Chí Minh",
        "post_date": "Cập nhật: 27/04/2021 - Bạn còn 7 ngày để ứng tuyển"
    },
    {
        "job_title": "Chuyên Viên Quản Lý Rủi Ro An Ninh Thông Tin",
        "company_name": "Novaland Group",
        "location": "Hồ Chí Minh",
        "post_date": "Cập nhật: 08/05/2021 - Bạn còn 18 ngày để ứng tuyển"
    },
    {
        "job_title": "Chuyên Viên Hệ Thống CNTT",
        "company_name": "Novaland Group",
        "location": "Hồ Chí Minh",
        "post_date": "Cập nhật: 08/05/2021 - Bạn còn 18 ngày để ứng tuyển"
    },
    {
        "job_title": "Information Technology Risk Consultant - Fresher/graduate",
        "company_name": "Chi Nhánh Công Ty TNHH KPMG",
        "location": "Hà Nội, Hồ Chí Minh",
        "post_date": "Cập nhật: 07/05/2021 - Bạn còn 20 ngày để ứng tuyển"
    },
    {
        "job_title": "Kỹ Sư DevOps",
        "company_name": "Digibank",
        "location": "Hà Nội, Hồ Chí Minh",
        "post_date": "Cập nhật: 07/05/2021 - Bạn còn 17 ngày để ứng tuyển"
    },
    {
        "job_title": "Team Lead-Service Management",
        "company_name": "Công Ty TNHH Linkbynet Việt Nam",
        "location": "Hồ Chí Minh",
        "post_date": "Cập nhật: 07/05/2021 - Bạn còn 28 ngày để ứng tuyển"
    },
    {
        "job_title": "Wealth Business Financial Manager",
        "company_name": "United Overseas Bank (Vietnam) Limited",
        "location": "Hồ Chí Minh",
        "post_date": "Cập nhật: 05/05/2021 - Bạn còn 11 ngày để ứng tuyển"
    },
    {
        "job_title": "Chuyên Viên Tuyển Dụng",
        "company_name": "Công Ty CP Hạ Tầng Viễn Thông CMC",
        "location": "Hà Nội, Hồ Chí Minh",
        "post_date": "Cập nhật: 02/05/2021 - Bạn còn 23 ngày để ứng tuyển"
    },
    {
        "job_title": "Talent Acquisition Consultant",
        "company_name": "We Are Bloom",
        "location": "Hồ Chí Minh",
        "post_date": "Cập nhật: 02/05/2021 - Bạn còn 12 ngày để ứng tuyển"
    },
    {
        "job_title": "Security Engineer (Salary: 1,800$ - 2500$)",
        "company_name": "Swiss Post Solutions Ltd.",
        "location": "Hồ Chí Minh",
        "post_date": "Cập nhật: 28/04/2021 - Bạn còn 4 ngày để ứng tuyển"
    },
    {
        "job_title": "Senior Project Manager - International Transforming FMCG",
        "company_name": "Page Group Vietnam",
        "location": "Hồ Chí Minh",
        "post_date": "Cập nhật: 26/04/2021 - Bạn còn 17 ngày để ứng tuyển"
    },
    {
        "job_title": "Chuyên Viên Cao Cấp Hệ Thống Công Nghệ Thông Tin",
        "company_name": "Novaland Group",
        "location": "Hồ Chí Minh",
        "post_date": "Cập nhật: 08/05/2021 - Bạn còn 18 ngày để ứng tuyển"
    },
    {
        "job_title": "Front-End Developer",
        "company_name": "Shuttlerock Vietnam",
        "location": "Hồ Chí Minh",
        "post_date": "Cập nhật: 07/05/2021 - Bạn còn 20 ngày để ứng tuyển"
    },
    {
        "job_title": "Giáo Viên Bộ Môn ICT",
        "company_name": "Trường Quốc Tế Nam Mỹ",
        "location": "Hồ Chí Minh",
        "post_date": "Cập nhật: 06/05/2021 - Bạn còn 12 ngày để ứng tuyển"
    },
    {
        "job_title": "Nhân Viên Lập Trình Web - Ưu Tiên Có Kinh Nghiệm Wordpress",
        "company_name": "Western Australian International School System ( WASS )",
        "location": "Hồ Chí Minh",
        "post_date": "Cập nhật: 05/05/2021 - Bạn còn 26 ngày để ứng tuyển"
    },
    {
        "job_title": "[HCM] - 3 Data Engineer (Up To 3000$) - Financial Field",
        "company_name": "Navigos Search's Client",
        "location": "Hồ Chí Minh",
        "post_date": "Cập nhật: 05/05/2021 - Bạn còn 11 ngày để ứng tuyển"
    },
    {
        "job_title": "Talent Acquisition Specialist",
        "company_name": "TRG International",
        "location": "Hồ Chí Minh",
        "post_date": "Cập nhật: 05/05/2021 - Bạn còn 26 ngày để ứng tuyển"
    },
    {
        "job_title": "Senior Frontend Engineer (ReactJS) - Remote Opportunity",
        "company_name": "Snaphunt",
        "location": "Hà Nội, Hồ Chí Minh, Quốc tế",
        "post_date": "Cập nhật: 28/04/2021 - Bạn còn 19 ngày để ứng tuyển"
    },
    {
        "job_title": "HR Assistant (Recruitment Focus)",
        "company_name": "Ekino.",
        "location": "Hồ Chí Minh",
        "post_date": "Cập nhật: 23/04/2021 - Bạn còn 3 ngày để ứng tuyển"
    },
    {
        "job_title": "Talent Acquisition Lead",
        "company_name": "Fram^",
        "location": "Hồ Chí Minh",
        "post_date": "Cập nhật: 03/05/2021 - Bạn còn 13 ngày để ứng tuyển"
    },
    {
        "job_title": "iOS Developer (Swift, Objective-C)",
        "company_name": "Ekino.",
        "location": "Hồ Chí Minh",
        "post_date": "Cập nhật: 30/04/2021 - Bạn còn 6 ngày để ứng tuyển"
    },
    {
        "job_title": "System Engineer",
        "company_name": "Netcompany",
        "location": "Hồ Chí Minh",
        "post_date": "Cập nhật: 07/05/2021 - Bạn còn 20 ngày để ứng tuyển"
    },
    {
        "job_title": "Core System Support Supervisor",
        "company_name": "Shinhan Vietnam Finance",
        "location": "Hồ Chí Minh",
        "post_date": "Cập nhật: 07/05/2021 - Bạn còn 17 ngày để ứng tuyển"
    },
    {
        "job_title": "HO - Transformation Initiative Project Manager",
        "company_name": "Ngân Hàng TMCP Á Châu (ACB)",
        "location": "Hồ Chí Minh",
        "post_date": "Cập nhật: 07/05/2021 - Bạn còn 28 ngày để ứng tuyển"
    },
    {
        "job_title": "Chuyên Viên Tin Học",
        "company_name": "Công Ty TNHH MTV Kiều Hối Ngân Hàng Thương Mại Cổ Phần Ngoại Thương Việt Nam",
        "location": "Hồ Chí Minh",
        "post_date": "Cập nhật: 01/05/2021 - Bạn còn 7 ngày để ứng tuyển"
    },
    {
        "job_title": "Chuyên Viên Phát Triển Ứng Dụng",
        "company_name": "Công Ty Cổ Phần Thuận Hải",
        "location": "Hồ Chí Minh",
        "post_date": "Cập nhật: 06/05/2021 - Bạn còn 27 ngày để ứng tuyển"
    },
    {
        "job_title": "Chuyên Viên Công Nghệ Thông Tin - Ban Kinh Doanh Thị Trường Điện",
        "company_name": "Tổng Công Ty Phát Điện 3",
        "location": "Hồ Chí Minh",
        "post_date": "Cập nhật: 07/05/2021 - Bạn còn 20 ngày để ứng tuyển"
    },
    {
        "job_title": "Quản Trị Mạng",
        "company_name": "Công Ty CP Giải Pháp Kinh Doanh Nền Tảng - Basebs",
        "location": "Hà Nội, Hồ Chí Minh",
        "post_date": "Cập nhật: 06/05/2021 - Hết hạn HÔM NAY!"
    },
    {
        "job_title": "DevOps Engineer",
        "company_name": "Công Ty Cổ Phần MicroAd Việt Nam",
        "location": "Hồ Chí Minh",
        "post_date": "Cập nhật: 05/05/2021 - Bạn còn 11 ngày để ứng tuyển"
    },
    {
        "job_title": "Transition Manager",
        "company_name": "Tập Đoàn CNTT Toàn Cầu HCL Technologies",
        "location": "Hồ Chí Minh",
        "post_date": "Cập nhật: 20/04/2021 - Hết hạn HÔM NAY!"
    },
    {
        "job_title": "Senior Front-End Development Engineer",
        "company_name": "Best Man POWER",
        "location": "Hồ Chí Minh",
        "post_date": "Cập nhật: 15/04/2021 - Bạn còn 6 ngày để ứng tuyển"
    },
    {
        "job_title": "Solution Architect",
        "company_name": "Aleph",
        "location": "Hồ Chí Minh",
        "post_date": "Cập nhật: 06/05/2021 - Bạn còn 12 ngày để ứng tuyển"
    }
]